[
  {"group": "ИС-235.1" "index": 2, "fio": "Фещенко Мария Владимировна"},
  {"group": "ИС-235.1" "index": 8, "fio": "Плотников Кирилл Русланович"},
  {"group": "ИС-235.1" "index": 7, "fio": "Филиппов Евгений Николаевич"},
  {"group": "ИС-235.1" "index": 6, "fio": "Бакаев Егор Владимирович"},
  {"group": "ИС-235.1" "index": 11, "fio": "Чесноков Данила Дмитриевич"},
  {"group": "ИС-235.1" "index": 1, "fio": "Миллер Тимур Артурович"},
  {"group": "ИС-235.1","index": 4,"fio": "Аносов Максим Денисович"},
  {"group": "ИС-235.1","index": 3,"fio": "Носков Илья Алексеевич"},
  {"group": "ИС-235.1","index": 5,"fio":"Белов Глеб Кириллович"},
  {"group": "ИС-235.1", "index": 1, "fio": "Исламов Илмас Илдарович"},
  {"group": "ИС-235.1", "index": 13, "fio": "Королев Матвей Евгеньевич"}
  {"group": "ИС-235.1", "index": 12, "fio": "Енин Алексей Ильич"},
  
]









